laboneq_applications/__init__.py
laboneq_applications/typing.py
laboneq_applications/analysis/__init__.py
laboneq_applications/analysis/amplitude_fine.py
laboneq_applications/analysis/amplitude_rabi.py
laboneq_applications/analysis/calibration_traces_rotation.py
laboneq_applications/analysis/dispersive_shift.py
laboneq_applications/analysis/drag_q_scaling.py
laboneq_applications/analysis/echo.py
laboneq_applications/analysis/fitting_helpers.py
laboneq_applications/analysis/iq_blobs.py
laboneq_applications/analysis/lifetime_measurement.py
laboneq_applications/analysis/options.py
laboneq_applications/analysis/plotting_helpers.py
laboneq_applications/analysis/qubit_spectroscopy.py
laboneq_applications/analysis/ramsey.py
laboneq_applications/analysis/resonator_spectroscopy.py
laboneq_applications/analysis/resonator_spectroscopy_dc_bias.py
laboneq_applications/analysis/spectroscopy_two_dimensional_plotting.py
laboneq_applications/analysis/time_traces.py
laboneq_applications/contrib/__init__.py
laboneq_applications/contrib/analysis/__init__.py
laboneq_applications/contrib/analysis/amplitude_rabi_chevron.py
laboneq_applications/contrib/analysis/calibrate_cancellation.py
laboneq_applications/contrib/analysis/measure_gain_curve.py
laboneq_applications/contrib/analysis/measurement_qndness.py
laboneq_applications/contrib/analysis/resonator_photons_time_resolved.py
laboneq_applications/contrib/analysis/scan_pump_parameters.py
laboneq_applications/contrib/analysis/signal_propagation_delay.py
laboneq_applications/contrib/analysis/single_qubit_randomized_benchmarking.py
laboneq_applications/contrib/analysis/time_rabi.py
laboneq_applications/contrib/analysis/time_rabi_chevron.py
laboneq_applications/contrib/analysis/zz_coupling_strength.py
laboneq_applications/contrib/experiments/__init__.py
laboneq_applications/contrib/experiments/amplitude_rabi_chevron.py
laboneq_applications/contrib/experiments/calibrate_cancellation.py
laboneq_applications-26.1.0.dist-info/licenses/LICENSE
laboneq_applications-26.1.0.dist-info/METADATA
laboneq_applications-26.1.0.dist-info/WHEEL
laboneq_applications-26.1.0.dist-info/top_level.txt
laboneq_applications-26.1.0.dist-info/RECORD
