Metadata-Version: 2.4
Name: laboneq_applications
Version: 26.1.0
Summary: Library of LabOne Q experiments, analysis functions, and more.
Author-email: Zurich Instruments Development Team <info@zhinst.com>
License: Apache 2.0
Project-URL: Changelog, https://docs.zhinst.com/labone_q_user_manual/release_notes/
Project-URL: Documentation, https://docs.zhinst.com/labone_q_user_manual/applications_library/
Project-URL: GitHub, https://github.com/zhinst/laboneq-applications
Keywords: quantum,sdk,zhinst
Classifier: Development Status :: 3 - Alpha
Classifier: Environment :: Console
Classifier: Intended Audience :: Developers
Classifier: Intended Audience :: Science/Research
Classifier: License :: OSI Approved :: Apache Software License
Classifier: Operating System :: MacOS
Classifier: Operating System :: Microsoft :: Windows
Classifier: Operating System :: POSIX :: Linux
Classifier: Programming Language :: Python :: 3.10
Classifier: Programming Language :: Python :: 3.11
Classifier: Programming Language :: Python :: 3.12
Classifier: Programming Language :: Python :: 3.13
Classifier: Topic :: Scientific/Engineering
Requires-Python: >=3.10
License-File: LICENSE
Requires-Dist: laboneq~=26.1.0
Requires-Dist: typing_extensions>=4.5.0
Requires-Dist: uncertainties>=3.2.2
Requires-Dist: numpy>=2
Requires-Dist: scipy>=1.12
Requires-Dist: matplotlib>=3.10
Requires-Dist: lmfit>=1.3.0
Requires-Dist: scikit-learn>=1.5.2
Requires-Dist: qiskit>=2.0.0
Requires-Dist: qiskit_experiments>=0.10.0
Dynamic: license-file
